ana_sdk/__init__.py
ana_sdk/ana.py
ana_sdk/clients/__init__.py
ana_sdk/clients/ana_data_client.py
ana_sdk/clients/base_client.py
ana_sdk/clients/dashboard_api_client.py
ana_sdk/clients/oauth_client.py
ana_sdk/clients/rpa_api_client.py
ana_sdk/exceptions/__init__.py
ana_sdk/requests_auth.py
ana_sdk/result_factory.py
ana_sdk/settings.py
ana_sdk-0.3.18.dist-info/METADATA
ana_sdk-0.3.18.dist-info/WHEEL
ana_sdk-0.3.18.dist-info/RECORD
