Metadata-Version: 2.1
Name: ana-sdk
Version: 0.3.18
Summary: SDK que visa fornecer uma interface para interagir com os serviços ANA.
License: MIT
Author: Jovane Mafort
Requires-Python: >=3.10.12,<4.0.0
Classifier: License :: OSI Approved :: MIT License
Classifier: Programming Language :: Python :: 3
Classifier: Programming Language :: Python :: 3.11
Requires-Dist: jsonschema (>=4.17.3,<5.0.0)
Requires-Dist: python-dotenv (>=1.0.0,<2.0.0)
Requires-Dist: requests (>=2.27.1,<3.0.0)
